python_laravel_queue/__init__.py
python_laravel_queue/queue.py
python_laravel_queue-0.0.1b2.dist-info/LICENSE
python_laravel_queue-0.0.1b2.dist-info/METADATA
python_laravel_queue-0.0.1b2.dist-info/WHEEL
python_laravel_queue-0.0.1b2.dist-info/top_level.txt
python_laravel_queue-0.0.1b2.dist-info/RECORD
