Metadata-Version: 2.1
Name: python-laravel-queue
Version: 0.0.1b2
Summary: Sync Laravel queue with Python.
Home-page: https://github.com/sinanbekar/python-laravel-queue
Author: Sinan Bekar
Author-email: sinanbekar.work@gmail.com
License: UNKNOWN
Project-URL: Bug Tracker, https://github.com/sinanbekar/python-laravel-queue/issues
Platform: UNKNOWN
Classifier: Programming Language :: Python :: 3
Classifier: License :: OSI Approved :: MIT License
Classifier: Operating System :: OS Independent
Requires-Python: >=3.6
License-File: LICENSE
Requires-Dist: redis
Requires-Dist: pyee
